{"name":"build-javascript","namedChunkGroups":{"polyfill":{"name":"polyfill","assets":[{"name":"webpack-runtime-80320bc61b1e5269afe6.js","size":3241},{"name":"polyfill-3e2ab4e5972a60843428.js","size":85830}],"filteredAssets":0,"assetsSize":89071,"filteredAuxiliaryAssets":2,"auxiliaryAssetsSize":221188},"app":{"name":"app","assets":[{"name":"webpack-runtime-80320bc61b1e5269afe6.js","size":3241},{"name":"framework-48544dcb7a41f5fd9f30.js","size":129735},{"name":"app-3ba31549d743ab9d7d00.js","size":52968}],"filteredAssets":0,"assetsSize":185944,"filteredAuxiliaryAssets":3,"auxiliaryAssetsSize":555033},"component---src-pages-404-js":{"name":"component---src-pages-404-js","assets":[{"name":"component---src-pages-404-js-ec54f9bfbf4cc37e9c3a.js","size":797}],"filteredAssets":0,"assetsSize":797,"filteredAuxiliaryAssets":1,"auxiliaryAssetsSize":1867},"component---src-pages-aboutme-js":{"name":"component---src-pages-aboutme-js","assets":[{"name":"component---src-pages-aboutme-js-9fa70e9d6b9a8e2da0f7.js","size":505}],"filteredAssets":0,"assetsSize":505,"filteredAuxiliaryAssets":1,"auxiliaryAssetsSize":718},"component---src-pages-index-js":{"name":"component---src-pages-index-js","assets":[{"name":"component---src-pages-index-js-cdf92202d2ae7beb8574.js","size":515}],"filteredAssets":0,"assetsSize":515,"filteredAuxiliaryAssets":1,"auxiliaryAssetsSize":727}},"assetsByChunkName":{"polyfill":["webpack-runtime-80320bc61b1e5269afe6.js","polyfill-3e2ab4e5972a60843428.js"],"app":["webpack-runtime-80320bc61b1e5269afe6.js","framework-48544dcb7a41f5fd9f30.js","app-3ba31549d743ab9d7d00.js"],"component---src-pages-404-js":["component---src-pages-404-js-ec54f9bfbf4cc37e9c3a.js"],"component---src-pages-aboutme-js":["component---src-pages-aboutme-js-9fa70e9d6b9a8e2da0f7.js"],"component---src-pages-index-js":["component---src-pages-index-js-cdf92202d2ae7beb8574.js"]},"childAssetsByChunkName":{}}